{
  "source_pdf": "/home/zzangmane/2025_null_Figure/pdfs/acl-2023/In-Context_Analogical_Reasoning_with_Pre-Trained_Language_Models_2023.acl-long.109.pdf",
  "page": 3,
  "figureType": null,
  "name": "3",
  "caption": "Figure 3: Example generated prompts for a complete RPM under entity attribute naming (left) and decomposition (right) abstractions in the Center sub-task.",
  "regionBoundary": {
    "x1": 79.67999999999999,
    "x2": 280.32,
    "y1": 81.6,
    "y2": 192.0
  },
  "score": 1.0,
  "reason": "The image explains a framework for categorizing objects by type, size, and color, showing an overall system."
}